{
  "repository_type": "multi-part",
  "total_parts": 2,
  "parts": [
    {
      "part_id": "client",
      "part_name": "CLIENT",
      "display_name": "Frontend (Vue.js SPA)",
      "project_type_id": "web",
      "root_path": "/Users/dim/code/crm_manufactur/client/",
      "primary_technology": "Vue.js 3",
      "framework": "Vite",
      "language": "JavaScript"
    },
    {
      "part_id": "server",
      "part_name": "SERVER",
      "display_name": "Backend (Express.js API)",
      "project_type_id": "backend",
      "root_path": "/Users/dim/code/crm_manufactur/server/",
      "primary_technology": "Express.js",
      "framework": "Express",
      "language": "JavaScript"
    }
  ],
  "integration_points": [
    {
      "from": "client",
      "to": "server",
      "type": "REST API",
      "protocol": "HTTP",
      "details": "Client calls server REST endpoints via api.js"
    }
  ]
}
